{
  "resourceType": "Bundle",
  "type": "transaction",
  "entry": [
    {
      "fullUrl": "Specimen/357289",
      "resource": {
        "resourceType": "Specimen",
        "id": "357289",
        "extension": [
          {
            "url": "https://fhir.centraxx.de/extension/updateWithOverwrite",
            "valueBoolean": false
          },
          {
            "url": "https://fhir.centraxx.de/extension/sample/repositionDate",
            "valueDateTime": "2024-01-15T09:55:37.000+01:00"
          },
          {
            "url": "https://fhir.centraxx.de/extension/sample/sampleLocation",
            "extension": [
              {
                "url": "https://fhir.centraxx.de/extension/sample/sampleLocationPath",
                "valueString": "NUM --> Klinikum Würzburg --> Ultra-Tiefkühlschrank POP -80°C"
              }
            ]
          },
          {
            "url": "https://fhir.centraxx.de/extension/sample/organizationUnit",
            "valueReference": {
              "identifier": {
                "value": "NUM_W_POP"
              }
            }
          },
          {
            "url": "https://fhir.centraxx.de/extension/sample/derivalDate",
            "valueDateTime": "2024-01-15T09:48:32.000+01:00"
          },
          {
            "url": "https://fhir.centraxx.de/extension/sampleCategory",
            "valueCoding": {
              "system": "urn:centraxx",
              "code": "DERIVED"
            }
          },
          {
            "url": "https://fhir.centraxx.de/extension/sprec",
            "extension": [
              {
                "url": "https://fhir.centraxx.de/extension/sprec/useSprec",
                "valueBoolean": false
              },
              {
                "url": "https://fhir.centraxx.de/extension/sprec/stockProcessing",
                "valueCoding": {
                  "system": "urn:centraxx",
                  "code": "NUM_BEGINN_ZENT"
                }
              }
            ]
          }
        ],
        "identifier": [
          {
            "type": {
              "coding": [
                {
                  "system": "urn:centraxx",
                  "code": "SAMPLEID"
                }
              ]
            },
            "value": "4080359619"
          }
        ],
        "status": "available",
        "type": {
          "coding": [
            {
              "system": "urn:centraxx",
              "code": "NUM_urinf"
            }
          ]
        },
        "subject": {
          "identifier": {
            "type": {
              "coding": [
                {
                  "system": "urn:centraxx",
                  "code": "LIMSPSN"
                }
              ]
            },
            "value": "lims_852751117"
          }
        },
        "parent": [
          {
            "reference": "Specimen/357288"
          }
        ],
        "collection": {
          "collectedDateTime": "2024-01-15T08:32:14+01:00",
          "quantity": {
            "value": 350,
            "unit": "MICL",
            "system": "urn:centraxx"
          }
        },
        "container": [
          {
            "identifier": [
              {
                "system": "urn:centraxx",
                "value": "NUM_AliContainer"
              }
            ],
            "capacity": {
              "value": 350,
              "unit": "MICL",
              "system": "urn:centraxx"
            },
            "specimenQuantity": {
              "value": 350,
              "unit": "MICL",
              "system": "urn:centraxx"
            }
          }
        ]
      },
      "request": {
        "method": "POST",
        "url": "Specimen/357289"
      }
    },
    {
      "fullUrl": "Specimen/357291",
      "resource": {
        "resourceType": "Specimen",
        "id": "357291",
        "extension": [
          {
            "url": "https://fhir.centraxx.de/extension/updateWithOverwrite",
            "valueBoolean": false
          },
          {
            "url": "https://fhir.centraxx.de/extension/sample/repositionDate",
            "valueDateTime": "2024-01-15T09:55:37.000+01:00"
          },
          {
            "url": "https://fhir.centraxx.de/extension/sample/sampleLocation",
            "extension": [
              {
                "url": "https://fhir.centraxx.de/extension/sample/sampleLocationPath",
                "valueString": "NUM --> Klinikum Würzburg --> Ultra-Tiefkühlschrank POP -80°C"
              }
            ]
          },
          {
            "url": "https://fhir.centraxx.de/extension/sample/organizationUnit",
            "valueReference": {
              "identifier": {
                "value": "NUM_W_POP"
              }
            }
          },
          {
            "url": "https://fhir.centraxx.de/extension/sample/derivalDate",
            "valueDateTime": "2024-01-15T09:48:33.000+01:00"
          },
          {
            "url": "https://fhir.centraxx.de/extension/sampleCategory",
            "valueCoding": {
              "system": "urn:centraxx",
              "code": "DERIVED"
            }
          },
          {
            "url": "https://fhir.centraxx.de/extension/sprec",
            "extension": [
              {
                "url": "https://fhir.centraxx.de/extension/sprec/useSprec",
                "valueBoolean": false
              },
              {
                "url": "https://fhir.centraxx.de/extension/sprec/stockProcessing",
                "valueCoding": {
                  "system": "urn:centraxx",
                  "code": "NUM_BEGINN_ZENT"
                }
              }
            ]
          }
        ],
        "identifier": [
          {
            "type": {
              "coding": [
                {
                  "system": "urn:centraxx",
                  "code": "SAMPLEID"
                }
              ]
            },
            "value": "4080359607"
          }
        ],
        "status": "available",
        "type": {
          "coding": [
            {
              "system": "urn:centraxx",
              "code": "NUM_urinf"
            }
          ]
        },
        "subject": {
          "identifier": {
            "type": {
              "coding": [
                {
                  "system": "urn:centraxx",
                  "code": "LIMSPSN"
                }
              ]
            },
            "value": "lims_852751117"
          }
        },
        "parent": [
          {
            "reference": "Specimen/357290"
          }
        ],
        "collection": {
          "collectedDateTime": "2024-01-15T08:32:14+01:00",
          "quantity": {
            "value": 350,
            "unit": "MICL",
            "system": "urn:centraxx"
          }
        },
        "container": [
          {
            "identifier": [
              {
                "system": "urn:centraxx",
                "value": "NUM_AliContainer"
              }
            ],
            "capacity": {
              "value": 350,
              "unit": "MICL",
              "system": "urn:centraxx"
            },
            "specimenQuantity": {
              "value": 350,
              "unit": "MICL",
              "system": "urn:centraxx"
            }
          }
        ]
      },
      "request": {
        "method": "POST",
        "url": "Specimen/357291"
      }
    },
    {
      "fullUrl": "Specimen/357293",
      "resource": {
        "resourceType": "Specimen",
        "id": "357293",
        "extension": [
          {
            "url": "https://fhir.centraxx.de/extension/updateWithOverwrite",
            "valueBoolean": false
          },
          {
            "url": "https://fhir.centraxx.de/extension/sample/repositionDate",
            "valueDateTime": "2024-01-15T09:55:37.000+01:00"
          },
          {
            "url": "https://fhir.centraxx.de/extension/sample/sampleLocation",
            "extension": [
              {
                "url": "https://fhir.centraxx.de/extension/sample/sampleLocationPath",
                "valueString": "NUM --> Klinikum Würzburg --> Ultra-Tiefkühlschrank POP -80°C"
              }
            ]
          },
          {
            "url": "https://fhir.centraxx.de/extension/sample/organizationUnit",
            "valueReference": {
              "identifier": {
                "value": "NUM_W_POP"
              }
            }
          },
          {
            "url": "https://fhir.centraxx.de/extension/sample/derivalDate",
            "valueDateTime": "2024-01-15T09:48:43.000+01:00"
          },
          {
            "url": "https://fhir.centraxx.de/extension/sampleCategory",
            "valueCoding": {
              "system": "urn:centraxx",
              "code": "DERIVED"
            }
          },
          {
            "url": "https://fhir.centraxx.de/extension/sprec",
            "extension": [
              {
                "url": "https://fhir.centraxx.de/extension/sprec/useSprec",
                "valueBoolean": false
              },
              {
                "url": "https://fhir.centraxx.de/extension/sprec/stockProcessing",
                "valueCoding": {
                  "system": "urn:centraxx",
                  "code": "NUM_BEGINN_ZENT"
                }
              }
            ]
          }
        ],
        "identifier": [
          {
            "type": {
              "coding": [
                {
                  "system": "urn:centraxx",
                  "code": "SAMPLEID"
                }
              ]
            },
            "value": "4080359606"
          }
        ],
        "status": "available",
        "type": {
          "coding": [
            {
              "system": "urn:centraxx",
              "code": "NUM_urins"
            }
          ]
        },
        "subject": {
          "identifier": {
            "type": {
              "coding": [
                {
                  "system": "urn:centraxx",
                  "code": "LIMSPSN"
                }
              ]
            },
            "value": "lims_852751117"
          }
        },
        "parent": [
          {
            "reference": "Specimen/357292"
          }
        ],
        "collection": {
          "collectedDateTime": "2024-01-15T08:32:14+01:00",
          "quantity": {
            "value": 350,
            "unit": "MICL",
            "system": "urn:centraxx"
          }
        },
        "container": [
          {
            "identifier": [
              {
                "system": "urn:centraxx",
                "value": "NUM_AliContainer"
              }
            ],
            "capacity": {
              "value": 350,
              "unit": "MICL",
              "system": "urn:centraxx"
            },
            "specimenQuantity": {
              "value": 350,
              "unit": "MICL",
              "system": "urn:centraxx"
            }
          }
        ]
      },
      "request": {
        "method": "POST",
        "url": "Specimen/357293"
      }
    },
    {
      "fullUrl": "Specimen/357295",
      "resource": {
        "resourceType": "Specimen",
        "id": "357295",
        "extension": [
          {
            "url": "https://fhir.centraxx.de/extension/updateWithOverwrite",
            "valueBoolean": false
          },
          {
            "url": "https://fhir.centraxx.de/extension/sample/repositionDate",
            "valueDateTime": "2024-01-15T09:55:37.000+01:00"
          },
          {
            "url": "https://fhir.centraxx.de/extension/sample/sampleLocation",
            "extension": [
              {
                "url": "https://fhir.centraxx.de/extension/sample/sampleLocationPath",
                "valueString": "NUM --> Klinikum Würzburg --> Ultra-Tiefkühlschrank POP -80°C"
              }
            ]
          },
          {
            "url": "https://fhir.centraxx.de/extension/sample/organizationUnit",
            "valueReference": {
              "identifier": {
                "value": "NUM_W_POP"
              }
            }
          },
          {
            "url": "https://fhir.centraxx.de/extension/sample/derivalDate",
            "valueDateTime": "2024-01-15T09:48:45.000+01:00"
          },
          {
            "url": "https://fhir.centraxx.de/extension/sampleCategory",
            "valueCoding": {
              "system": "urn:centraxx",
              "code": "DERIVED"
            }
          },
          {
            "url": "https://fhir.centraxx.de/extension/sprec",
            "extension": [
              {
                "url": "https://fhir.centraxx.de/extension/sprec/useSprec",
                "valueBoolean": false
              },
              {
                "url": "https://fhir.centraxx.de/extension/sprec/stockProcessing",
                "valueCoding": {
                  "system": "urn:centraxx",
                  "code": "NUM_BEGINN_ZENT"
                }
              }
            ]
          }
        ],
        "identifier": [
          {
            "type": {
              "coding": [
                {
                  "system": "urn:centraxx",
                  "code": "SAMPLEID"
                }
              ]
            },
            "value": "4080359594"
          }
        ],
        "status": "available",
        "type": {
          "coding": [
            {
              "system": "urn:centraxx",
              "code": "NUM_urins"
            }
          ]
        },
        "subject": {
          "identifier": {
            "type": {
              "coding": [
                {
                  "system": "urn:centraxx",
                  "code": "LIMSPSN"
                }
              ]
            },
            "value": "lims_852751117"
          }
        },
        "parent": [
          {
            "reference": "Specimen/357294"
          }
        ],
        "collection": {
          "collectedDateTime": "2024-01-15T08:32:14+01:00",
          "quantity": {
            "value": 350,
            "unit": "MICL",
            "system": "urn:centraxx"
          }
        },
        "container": [
          {
            "identifier": [
              {
                "system": "urn:centraxx",
                "value": "NUM_AliContainer"
              }
            ],
            "capacity": {
              "value": 350,
              "unit": "MICL",
              "system": "urn:centraxx"
            },
            "specimenQuantity": {
              "value": 350,
              "unit": "MICL",
              "system": "urn:centraxx"
            }
          }
        ]
      },
      "request": {
        "method": "POST",
        "url": "Specimen/357295"
      }
    },
    {
      "fullUrl": "Specimen/357303",
      "resource": {
        "resourceType": "Specimen",
        "id": "357303",
        "extension": [
          {
            "url": "https://fhir.centraxx.de/extension/updateWithOverwrite",
            "valueBoolean": false
          },
          {
            "url": "https://fhir.centraxx.de/extension/sample/repositionDate",
            "valueDateTime": "2024-01-15T09:55:37.000+01:00"
          },
          {
            "url": "https://fhir.centraxx.de/extension/sample/sampleLocation",
            "extension": [
              {
                "url": "https://fhir.centraxx.de/extension/sample/sampleLocationPath",
                "valueString": "NUM --> Klinikum Würzburg --> Ultra-Tiefkühlschrank POP -80°C"
              }
            ]
          },
          {
            "url": "https://fhir.centraxx.de/extension/sample/organizationUnit",
            "valueReference": {
              "identifier": {
                "value": "NUM_W_POP"
              }
            }
          },
          {
            "url": "https://fhir.centraxx.de/extension/sample/derivalDate",
            "valueDateTime": "2024-01-15T09:50:07.000+01:00"
          },
          {
            "url": "https://fhir.centraxx.de/extension/sampleCategory",
            "valueCoding": {
              "system": "urn:centraxx",
              "code": "DERIVED"
            }
          },
          {
            "url": "https://fhir.centraxx.de/extension/sprec",
            "extension": [
              {
                "url": "https://fhir.centraxx.de/extension/sprec/useSprec",
                "valueBoolean": false
              },
              {
                "url": "https://fhir.centraxx.de/extension/sprec/stockProcessing",
                "valueCoding": {
                  "system": "urn:centraxx",
                  "code": "Sprec-B"
                }
              }
            ]
          }
        ],
        "identifier": [
          {
            "type": {
              "coding": [
                {
                  "system": "urn:centraxx",
                  "code": "SAMPLEID"
                }
              ]
            },
            "value": "4080431379"
          }
        ],
        "status": "available",
        "type": {
          "coding": [
            {
              "system": "urn:centraxx",
              "code": "SER"
            }
          ]
        },
        "subject": {
          "identifier": {
            "type": {
              "coding": [
                {
                  "system": "urn:centraxx",
                  "code": "LIMSPSN"
                }
              ]
            },
            "value": "lims_852751117"
          }
        },
        "parent": [
          {
            "reference": "Specimen/357302"
          }
        ],
        "collection": {
          "collectedDateTime": "2024-01-15T08:27:45+01:00",
          "quantity": {
            "value": 350,
            "unit": "MICL",
            "system": "urn:centraxx"
          }
        },
        "container": [
          {
            "identifier": [
              {
                "system": "urn:centraxx",
                "value": "NUM_AliContainer"
              }
            ],
            "capacity": {
              "value": 350,
              "unit": "MICL",
              "system": "urn:centraxx"
            },
            "specimenQuantity": {
              "value": 350,
              "unit": "MICL",
              "system": "urn:centraxx"
            }
          }
        ]
      },
      "request": {
        "method": "POST",
        "url": "Specimen/357303"
      }
    },
    {
      "fullUrl": "Specimen/357314",
      "resource": {
        "resourceType": "Specimen",
        "id": "357314",
        "extension": [
          {
            "url": "https://fhir.centraxx.de/extension/updateWithOverwrite",
            "valueBoolean": false
          },
          {
            "url": "https://fhir.centraxx.de/extension/sample/repositionDate",
            "valueDateTime": "2024-01-15T09:55:37.000+01:00"
          },
          {
            "url": "https://fhir.centraxx.de/extension/sample/sampleLocation",
            "extension": [
              {
                "url": "https://fhir.centraxx.de/extension/sample/sampleLocationPath",
                "valueString": "NUM --> Klinikum Würzburg --> Ultra-Tiefkühlschrank POP -80°C"
              }
            ]
          },
          {
            "url": "https://fhir.centraxx.de/extension/sample/organizationUnit",
            "valueReference": {
              "identifier": {
                "value": "NUM_W_POP"
              }
            }
          },
          {
            "url": "https://fhir.centraxx.de/extension/sample/derivalDate",
            "valueDateTime": "2024-01-15T09:52:09.000+01:00"
          },
          {
            "url": "https://fhir.centraxx.de/extension/sampleCategory",
            "valueCoding": {
              "system": "urn:centraxx",
              "code": "DERIVED"
            }
          },
          {
            "url": "https://fhir.centraxx.de/extension/sprec",
            "extension": [
              {
                "url": "https://fhir.centraxx.de/extension/sprec/useSprec",
                "valueBoolean": false
              },
              {
                "url": "https://fhir.centraxx.de/extension/sprec/stockProcessing",
                "valueCoding": {
                  "system": "urn:centraxx",
                  "code": "Sprec-B"
                }
              }
            ]
          }
        ],
        "identifier": [
          {
            "type": {
              "coding": [
                {
                  "system": "urn:centraxx",
                  "code": "SAMPLEID"
                }
              ]
            },
            "value": "4080359612"
          }
        ],
        "status": "available",
        "type": {
          "coding": [
            {
              "system": "urn:centraxx",
              "code": "EDTA"
            }
          ]
        },
        "subject": {
          "identifier": {
            "type": {
              "coding": [
                {
                  "system": "urn:centraxx",
                  "code": "LIMSPSN"
                }
              ]
            },
            "value": "lims_852751117"
          }
        },
        "parent": [
          {
            "reference": "Specimen/357313"
          }
        ],
        "collection": {
          "collectedDateTime": "2024-01-15T08:27:54+01:00",
          "quantity": {
            "value": 350,
            "unit": "MICL",
            "system": "urn:centraxx"
          }
        },
        "container": [
          {
            "identifier": [
              {
                "system": "urn:centraxx",
                "value": "NUM_AliContainer"
              }
            ],
            "capacity": {
              "value": 350,
              "unit": "MICL",
              "system": "urn:centraxx"
            },
            "specimenQuantity": {
              "value": 350,
              "unit": "MICL",
              "system": "urn:centraxx"
            }
          }
        ]
      },
      "request": {
        "method": "POST",
        "url": "Specimen/357314"
      }
    },
    {
      "fullUrl": "Specimen/357316",
      "resource": {
        "resourceType": "Specimen",
        "id": "357316",
        "extension": [
          {
            "url": "https://fhir.centraxx.de/extension/updateWithOverwrite",
            "valueBoolean": false
          },
          {
            "url": "https://fhir.centraxx.de/extension/sample/repositionDate",
            "valueDateTime": "2024-01-15T09:55:37.000+01:00"
          },
          {
            "url": "https://fhir.centraxx.de/extension/sample/sampleLocation",
            "extension": [
              {
                "url": "https://fhir.centraxx.de/extension/sample/sampleLocationPath",
                "valueString": "NUM --> Klinikum Würzburg --> Ultra-Tiefkühlschrank POP -80°C"
              }
            ]
          },
          {
            "url": "https://fhir.centraxx.de/extension/sample/organizationUnit",
            "valueReference": {
              "identifier": {
                "value": "NUM_W_POP"
              }
            }
          },
          {
            "url": "https://fhir.centraxx.de/extension/sample/derivalDate",
            "valueDateTime": "2024-01-15T09:52:12.000+01:00"
          },
          {
            "url": "https://fhir.centraxx.de/extension/sampleCategory",
            "valueCoding": {
              "system": "urn:centraxx",
              "code": "DERIVED"
            }
          },
          {
            "url": "https://fhir.centraxx.de/extension/sprec",
            "extension": [
              {
                "url": "https://fhir.centraxx.de/extension/sprec/useSprec",
                "valueBoolean": false
              },
              {
                "url": "https://fhir.centraxx.de/extension/sprec/stockProcessing",
                "valueCoding": {
                  "system": "urn:centraxx",
                  "code": "Sprec-B"
                }
              }
            ]
          }
        ],
        "identifier": [
          {
            "type": {
              "coding": [
                {
                  "system": "urn:centraxx",
                  "code": "SAMPLEID"
                }
              ]
            },
            "value": "4080359590"
          }
        ],
        "status": "available",
        "type": {
          "coding": [
            {
              "system": "urn:centraxx",
              "code": "EDTA"
            }
          ]
        },
        "subject": {
          "identifier": {
            "type": {
              "coding": [
                {
                  "system": "urn:centraxx",
                  "code": "LIMSPSN"
                }
              ]
            },
            "value": "lims_852751117"
          }
        },
        "parent": [
          {
            "reference": "Specimen/357315"
          }
        ],
        "collection": {
          "collectedDateTime": "2024-01-15T08:27:54+01:00",
          "quantity": {
            "value": 350,
            "unit": "MICL",
            "system": "urn:centraxx"
          }
        },
        "container": [
          {
            "identifier": [
              {
                "system": "urn:centraxx",
                "value": "NUM_AliContainer"
              }
            ],
            "capacity": {
              "value": 350,
              "unit": "MICL",
              "system": "urn:centraxx"
            },
            "specimenQuantity": {
              "value": 350,
              "unit": "MICL",
              "system": "urn:centraxx"
            }
          }
        ]
      },
      "request": {
        "method": "POST",
        "url": "Specimen/357316"
      }
    },
    {
      "fullUrl": "Specimen/357318",
      "resource": {
        "resourceType": "Specimen",
        "id": "357318",
        "extension": [
          {
            "url": "https://fhir.centraxx.de/extension/updateWithOverwrite",
            "valueBoolean": false
          },
          {
            "url": "https://fhir.centraxx.de/extension/sample/repositionDate",
            "valueDateTime": "2024-01-15T09:55:37.000+01:00"
          },
          {
            "url": "https://fhir.centraxx.de/extension/sample/sampleLocation",
            "extension": [
              {
                "url": "https://fhir.centraxx.de/extension/sample/sampleLocationPath",
                "valueString": "NUM --> Klinikum Würzburg --> Ultra-Tiefkühlschrank POP -80°C"
              }
            ]
          },
          {
            "url": "https://fhir.centraxx.de/extension/sample/organizationUnit",
            "valueReference": {
              "identifier": {
                "value": "NUM_W_POP"
              }
            }
          },
          {
            "url": "https://fhir.centraxx.de/extension/sample/derivalDate",
            "valueDateTime": "2024-01-15T09:52:16.000+01:00"
          },
          {
            "url": "https://fhir.centraxx.de/extension/sampleCategory",
            "valueCoding": {
              "system": "urn:centraxx",
              "code": "DERIVED"
            }
          },
          {
            "url": "https://fhir.centraxx.de/extension/sprec",
            "extension": [
              {
                "url": "https://fhir.centraxx.de/extension/sprec/useSprec",
                "valueBoolean": false
              },
              {
                "url": "https://fhir.centraxx.de/extension/sprec/stockProcessing",
                "valueCoding": {
                  "system": "urn:centraxx",
                  "code": "Sprec-B"
                }
              }
            ]
          }
        ],
        "identifier": [
          {
            "type": {
              "coding": [
                {
                  "system": "urn:centraxx",
                  "code": "SAMPLEID"
                }
              ]
            },
            "value": "4080359605"
          }
        ],
        "status": "available",
        "type": {
          "coding": [
            {
              "system": "urn:centraxx",
              "code": "EDTA"
            }
          ]
        },
        "subject": {
          "identifier": {
            "type": {
              "coding": [
                {
                  "system": "urn:centraxx",
                  "code": "LIMSPSN"
                }
              ]
            },
            "value": "lims_852751117"
          }
        },
        "parent": [
          {
            "reference": "Specimen/357317"
          }
        ],
        "collection": {
          "collectedDateTime": "2024-01-15T08:27:54+01:00",
          "quantity": {
            "value": 350,
            "unit": "MICL",
            "system": "urn:centraxx"
          }
        },
        "container": [
          {
            "identifier": [
              {
                "system": "urn:centraxx",
                "value": "NUM_AliContainer"
              }
            ],
            "capacity": {
              "value": 350,
              "unit": "MICL",
              "system": "urn:centraxx"
            },
            "specimenQuantity": {
              "value": 350,
              "unit": "MICL",
              "system": "urn:centraxx"
            }
          }
        ]
      },
      "request": {
        "method": "POST",
        "url": "Specimen/357318"
      }
    },
    {
      "fullUrl": "Specimen/357320",
      "resource": {
        "resourceType": "Specimen",
        "id": "357320",
        "extension": [
          {
            "url": "https://fhir.centraxx.de/extension/updateWithOverwrite",
            "valueBoolean": false
          },
          {
            "url": "https://fhir.centraxx.de/extension/sample/repositionDate",
            "valueDateTime": "2024-01-15T09:55:37.000+01:00"
          },
          {
            "url": "https://fhir.centraxx.de/extension/sample/sampleLocation",
            "extension": [
              {
                "url": "https://fhir.centraxx.de/extension/sample/sampleLocationPath",
                "valueString": "NUM --> Klinikum Würzburg --> Ultra-Tiefkühlschrank POP -80°C"
              }
            ]
          },
          {
            "url": "https://fhir.centraxx.de/extension/sample/organizationUnit",
            "valueReference": {
              "identifier": {
                "value": "NUM_W_POP"
              }
            }
          },
          {
            "url": "https://fhir.centraxx.de/extension/sample/derivalDate",
            "valueDateTime": "2024-01-15T09:52:25.000+01:00"
          },
          {
            "url": "https://fhir.centraxx.de/extension/sampleCategory",
            "valueCoding": {
              "system": "urn:centraxx",
              "code": "DERIVED"
            }
          },
          {
            "url": "https://fhir.centraxx.de/extension/sprec",
            "extension": [
              {
                "url": "https://fhir.centraxx.de/extension/sprec/useSprec",
                "valueBoolean": false
              },
              {
                "url": "https://fhir.centraxx.de/extension/sprec/stockProcessing",
                "valueCoding": {
                  "system": "urn:centraxx",
                  "code": "Sprec-B"
                }
              }
            ]
          }
        ],
        "identifier": [
          {
            "type": {
              "coding": [
                {
                  "system": "urn:centraxx",
                  "code": "SAMPLEID"
                }
              ]
            },
            "value": "4080359593"
          }
        ],
        "status": "available",
        "type": {
          "coding": [
            {
              "system": "urn:centraxx",
              "code": "EDTABUF"
            }
          ]
        },
        "subject": {
          "identifier": {
            "type": {
              "coding": [
                {
                  "system": "urn:centraxx",
                  "code": "LIMSPSN"
                }
              ]
            },
            "value": "lims_852751117"
          }
        },
        "parent": [
          {
            "reference": "Specimen/357319"
          }
        ],
        "collection": {
          "collectedDateTime": "2024-01-15T08:27:54+01:00",
          "quantity": {
            "value": 350,
            "unit": "MICL",
            "system": "urn:centraxx"
          }
        },
        "container": [
          {
            "identifier": [
              {
                "system": "urn:centraxx",
                "value": "NUM_AliContainer"
              }
            ],
            "capacity": {
              "value": 350,
              "unit": "MICL",
              "system": "urn:centraxx"
            },
            "specimenQuantity": {
              "value": 350,
              "unit": "MICL",
              "system": "urn:centraxx"
            }
          }
        ]
      },
      "request": {
        "method": "POST",
        "url": "Specimen/357320"
      }
    },
    {
      "fullUrl": "Specimen/357322",
      "resource": {
        "resourceType": "Specimen",
        "id": "357322",
        "extension": [
          {
            "url": "https://fhir.centraxx.de/extension/updateWithOverwrite",
            "valueBoolean": false
          },
          {
            "url": "https://fhir.centraxx.de/extension/sample/repositionDate",
            "valueDateTime": "2024-01-15T09:55:37.000+01:00"
          },
          {
            "url": "https://fhir.centraxx.de/extension/sample/sampleLocation",
            "extension": [
              {
                "url": "https://fhir.centraxx.de/extension/sample/sampleLocationPath",
                "valueString": "NUM --> Klinikum Würzburg --> Ultra-Tiefkühlschrank POP -80°C"
              }
            ]
          },
          {
            "url": "https://fhir.centraxx.de/extension/sample/organizationUnit",
            "valueReference": {
              "identifier": {
                "value": "NUM_W_POP"
              }
            }
          },
          {
            "url": "https://fhir.centraxx.de/extension/sample/derivalDate",
            "valueDateTime": "2024-01-15T09:52:31.000+01:00"
          },
          {
            "url": "https://fhir.centraxx.de/extension/sampleCategory",
            "valueCoding": {
              "system": "urn:centraxx",
              "code": "DERIVED"
            }
          },
          {
            "url": "https://fhir.centraxx.de/extension/sprec",
            "extension": [
              {
                "url": "https://fhir.centraxx.de/extension/sprec/useSprec",
                "valueBoolean": false
              },
              {
                "url": "https://fhir.centraxx.de/extension/sprec/stockProcessing",
                "valueCoding": {
                  "system": "urn:centraxx",
                  "code": "Sprec-B"
                }
              }
            ]
          }
        ],
        "identifier": [
          {
            "type": {
              "coding": [
                {
                  "system": "urn:centraxx",
                  "code": "SAMPLEID"
                }
              ]
            },
            "value": "4080431367"
          }
        ],
        "status": "available",
        "type": {
          "coding": [
            {
              "system": "urn:centraxx",
              "code": "EDTA"
            }
          ]
        },
        "subject": {
          "identifier": {
            "type": {
              "coding": [
                {
                  "system": "urn:centraxx",
                  "code": "LIMSPSN"
                }
              ]
            },
            "value": "lims_852751117"
          }
        },
        "parent": [
          {
            "reference": "Specimen/357321"
          }
        ],
        "collection": {
          "collectedDateTime": "2024-01-15T08:27:31+01:00",
          "quantity": {
            "value": 350,
            "unit": "MICL",
            "system": "urn:centraxx"
          }
        },
        "container": [
          {
            "identifier": [
              {
                "system": "urn:centraxx",
                "value": "NUM_AliContainer"
              }
            ],
            "capacity": {
              "value": 350,
              "unit": "MICL",
              "system": "urn:centraxx"
            },
            "specimenQuantity": {
              "value": 350,
              "unit": "MICL",
              "system": "urn:centraxx"
            }
          }
        ]
      },
      "request": {
        "method": "POST",
        "url": "Specimen/357322"
      }
    },
    {
      "fullUrl": "Specimen/357324",
      "resource": {
        "resourceType": "Specimen",
        "id": "357324",
        "extension": [
          {
            "url": "https://fhir.centraxx.de/extension/updateWithOverwrite",
            "valueBoolean": false
          },
          {
            "url": "https://fhir.centraxx.de/extension/sample/repositionDate",
            "valueDateTime": "2024-01-15T09:55:37.000+01:00"
          },
          {
            "url": "https://fhir.centraxx.de/extension/sample/sampleLocation",
            "extension": [
              {
                "url": "https://fhir.centraxx.de/extension/sample/sampleLocationPath",
                "valueString": "NUM --> Klinikum Würzburg --> Ultra-Tiefkühlschrank POP -80°C"
              }
            ]
          },
          {
            "url": "https://fhir.centraxx.de/extension/sample/organizationUnit",
            "valueReference": {
              "identifier": {
                "value": "NUM_W_POP"
              }
            }
          },
          {
            "url": "https://fhir.centraxx.de/extension/sample/derivalDate",
            "valueDateTime": "2024-01-15T09:52:33.000+01:00"
          },
          {
            "url": "https://fhir.centraxx.de/extension/sampleCategory",
            "valueCoding": {
              "system": "urn:centraxx",
              "code": "DERIVED"
            }
          },
          {
            "url": "https://fhir.centraxx.de/extension/sprec",
            "extension": [
              {
                "url": "https://fhir.centraxx.de/extension/sprec/useSprec",
                "valueBoolean": false
              },
              {
                "url": "https://fhir.centraxx.de/extension/sprec/stockProcessing",
                "valueCoding": {
                  "system": "urn:centraxx",
                  "code": "Sprec-B"
                }
              }
            ]
          }
        ],
        "identifier": [
          {
            "type": {
              "coding": [
                {
                  "system": "urn:centraxx",
                  "code": "SAMPLEID"
                }
              ]
            },
            "value": "4080431355"
          }
        ],
        "status": "available",
        "type": {
          "coding": [
            {
              "system": "urn:centraxx",
              "code": "EDTA"
            }
          ]
        },
        "subject": {
          "identifier": {
            "type": {
              "coding": [
                {
                  "system": "urn:centraxx",
                  "code": "LIMSPSN"
                }
              ]
            },
            "value": "lims_852751117"
          }
        },
        "parent": [
          {
            "reference": "Specimen/357323"
          }
        ],
        "collection": {
          "collectedDateTime": "2024-01-15T08:27:31+01:00",
          "quantity": {
            "value": 350,
            "unit": "MICL",
            "system": "urn:centraxx"
          }
        },
        "container": [
          {
            "identifier": [
              {
                "system": "urn:centraxx",
                "value": "NUM_AliContainer"
              }
            ],
            "capacity": {
              "value": 350,
              "unit": "MICL",
              "system": "urn:centraxx"
            },
            "specimenQuantity": {
              "value": 350,
              "unit": "MICL",
              "system": "urn:centraxx"
            }
          }
        ]
      },
      "request": {
        "method": "POST",
        "url": "Specimen/357324"
      }
    },
    {
      "fullUrl": "Specimen/357326",
      "resource": {
        "resourceType": "Specimen",
        "id": "357326",
        "extension": [
          {
            "url": "https://fhir.centraxx.de/extension/updateWithOverwrite",
            "valueBoolean": false
          },
          {
            "url": "https://fhir.centraxx.de/extension/sample/repositionDate",
            "valueDateTime": "2024-01-15T09:55:37.000+01:00"
          },
          {
            "url": "https://fhir.centraxx.de/extension/sample/sampleLocation",
            "extension": [
              {
                "url": "https://fhir.centraxx.de/extension/sample/sampleLocationPath",
                "valueString": "NUM --> Klinikum Würzburg --> Ultra-Tiefkühlschrank POP -80°C"
              }
            ]
          },
          {
            "url": "https://fhir.centraxx.de/extension/sample/organizationUnit",
            "valueReference": {
              "identifier": {
                "value": "NUM_W_POP"
              }
            }
          },
          {
            "url": "https://fhir.centraxx.de/extension/sample/derivalDate",
            "valueDateTime": "2024-01-15T09:52:36.000+01:00"
          },
          {
            "url": "https://fhir.centraxx.de/extension/sampleCategory",
            "valueCoding": {
              "system": "urn:centraxx",
              "code": "DERIVED"
            }
          },
          {
            "url": "https://fhir.centraxx.de/extension/sprec",
            "extension": [
              {
                "url": "https://fhir.centraxx.de/extension/sprec/useSprec",
                "valueBoolean": false
              },
              {
                "url": "https://fhir.centraxx.de/extension/sprec/stockProcessing",
                "valueCoding": {
                  "system": "urn:centraxx",
                  "code": "Sprec-B"
                }
              }
            ]
          }
        ],
        "identifier": [
          {
            "type": {
              "coding": [
                {
                  "system": "urn:centraxx",
                  "code": "SAMPLEID"
                }
              ]
            },
            "value": "4080431343"
          }
        ],
        "status": "available",
        "type": {
          "coding": [
            {
              "system": "urn:centraxx",
              "code": "EDTA"
            }
          ]
        },
        "subject": {
          "identifier": {
            "type": {
              "coding": [
                {
                  "system": "urn:centraxx",
                  "code": "LIMSPSN"
                }
              ]
            },
            "value": "lims_852751117"
          }
        },
        "parent": [
          {
            "reference": "Specimen/357325"
          }
        ],
        "collection": {
          "collectedDateTime": "2024-01-15T08:27:31+01:00",
          "quantity": {
            "value": 350,
            "unit": "MICL",
            "system": "urn:centraxx"
          }
        },
        "container": [
          {
            "identifier": [
              {
                "system": "urn:centraxx",
                "value": "NUM_AliContainer"
              }
            ],
            "capacity": {
              "value": 350,
              "unit": "MICL",
              "system": "urn:centraxx"
            },
            "specimenQuantity": {
              "value": 350,
              "unit": "MICL",
              "system": "urn:centraxx"
            }
          }
        ]
      },
      "request": {
        "method": "POST",
        "url": "Specimen/357326"
      }
    },
    {
      "fullUrl": "Specimen/357328",
      "resource": {
        "resourceType": "Specimen",
        "id": "357328",
        "extension": [
          {
            "url": "https://fhir.centraxx.de/extension/updateWithOverwrite",
            "valueBoolean": false
          },
          {
            "url": "https://fhir.centraxx.de/extension/sample/repositionDate",
            "valueDateTime": "2024-01-15T09:55:37.000+01:00"
          },
          {
            "url": "https://fhir.centraxx.de/extension/sample/sampleLocation",
            "extension": [
              {
                "url": "https://fhir.centraxx.de/extension/sample/sampleLocationPath",
                "valueString": "NUM --> Klinikum Würzburg --> Ultra-Tiefkühlschrank POP -80°C"
              }
            ]
          },
          {
            "url": "https://fhir.centraxx.de/extension/sample/organizationUnit",
            "valueReference": {
              "identifier": {
                "value": "NUM_W_POP"
              }
            }
          },
          {
            "url": "https://fhir.centraxx.de/extension/sample/derivalDate",
            "valueDateTime": "2024-01-15T09:52:46.000+01:00"
          },
          {
            "url": "https://fhir.centraxx.de/extension/sampleCategory",
            "valueCoding": {
              "system": "urn:centraxx",
              "code": "DERIVED"
            }
          },
          {
            "url": "https://fhir.centraxx.de/extension/sprec",
            "extension": [
              {
                "url": "https://fhir.centraxx.de/extension/sprec/useSprec",
                "valueBoolean": false
              },
              {
                "url": "https://fhir.centraxx.de/extension/sprec/stockProcessing",
                "valueCoding": {
                  "system": "urn:centraxx",
                  "code": "Sprec-B"
                }
              }
            ]
          }
        ],
        "identifier": [
          {
            "type": {
              "coding": [
                {
                  "system": "urn:centraxx",
                  "code": "SAMPLEID"
                }
              ]
            },
            "value": "4080431426"
          }
        ],
        "status": "available",
        "type": {
          "coding": [
            {
              "system": "urn:centraxx",
              "code": "EDTABUF"
            }
          ]
        },
        "subject": {
          "identifier": {
            "type": {
              "coding": [
                {
                  "system": "urn:centraxx",
                  "code": "LIMSPSN"
                }
              ]
            },
            "value": "lims_852751117"
          }
        },
        "parent": [
          {
            "reference": "Specimen/357327"
          }
        ],
        "collection": {
          "collectedDateTime": "2024-01-15T08:27:31+01:00",
          "quantity": {
            "value": 350,
            "unit": "MICL",
            "system": "urn:centraxx"
          }
        },
        "container": [
          {
            "identifier": [
              {
                "system": "urn:centraxx",
                "value": "NUM_AliContainer"
              }
            ],
            "capacity": {
              "value": 350,
              "unit": "MICL",
              "system": "urn:centraxx"
            },
            "specimenQuantity": {
              "value": 350,
              "unit": "MICL",
              "system": "urn:centraxx"
            }
          }
        ]
      },
      "request": {
        "method": "POST",
        "url": "Specimen/357328"
      }
    },
    {
      "fullUrl": "Specimen/357338",
      "resource": {
        "resourceType": "Specimen",
        "id": "357338",
        "extension": [
          {
            "url": "https://fhir.centraxx.de/extension/updateWithOverwrite",
            "valueBoolean": false
          },
          {
            "url": "https://fhir.centraxx.de/extension/sample/repositionDate",
            "valueDateTime": "2024-01-15T15:34:35.000+01:00"
          },
          {
            "url": "https://fhir.centraxx.de/extension/sample/sampleLocation",
            "extension": [
              {
                "url": "https://fhir.centraxx.de/extension/sample/sampleLocationPath",
                "valueString": "NUM --> Klinikum Würzburg --> N2 Tank POP -196°C"
              }
            ]
          },
          {
            "url": "https://fhir.centraxx.de/extension/sample/organizationUnit",
            "valueReference": {
              "identifier": {
                "value": "NUM_W_POP"
              }
            }
          },
          {
            "url": "https://fhir.centraxx.de/extension/sample/derivalDate",
            "valueDateTime": "2024-01-15T10:27:18.000+01:00"
          },
          {
            "url": "https://fhir.centraxx.de/extension/sampleCategory",
            "valueCoding": {
              "system": "urn:centraxx",
              "code": "DERIVED"
            }
          },
          {
            "url": "https://fhir.centraxx.de/extension/sample/concentration",
            "valueQuantity": {
              "value": 10,
              "unit": "XE06ML"
            }
          },
          {
            "url": "https://fhir.centraxx.de/extension/sprec",
            "extension": [
              {
                "url": "https://fhir.centraxx.de/extension/sprec/useSprec",
                "valueBoolean": false
              },
              {
                "url": "https://fhir.centraxx.de/extension/sprec/primarySampleContainer",
                "valueCoding": {
                  "system": "urn:centraxx",
                  "code": "CPT"
                }
              },
              {
                "url": "https://fhir.centraxx.de/extension/sprec/stockProcessing",
                "valueCoding": {
                  "system": "urn:centraxx",
                  "code": "NUM_BEGINN_ZENT"
                }
              },
              {
                "url": "https://fhir.centraxx.de/extension/sprec/secondProcessing",
                "valueCoding": {
                  "system": "urn:centraxx",
                  "code": "NUM_RT15min300gBremse"
                }
              }
            ]
          }
        ],
        "identifier": [
          {
            "type": {
              "coding": [
                {
                  "system": "urn:centraxx",
                  "code": "SAMPLEID"
                }
              ]
            },
            "value": "4080359563"
          }
        ],
        "status": "available",
        "type": {
          "coding": [
            {
              "system": "urn:centraxx",
              "code": "NUM_PBMC_C"
            }
          ]
        },
        "subject": {
          "identifier": {
            "type": {
              "coding": [
                {
                  "system": "urn:centraxx",
                  "code": "LIMSPSN"
                }
              ]
            },
            "value": "lims_852751117"
          }
        },
        "receivedTime": "2024-01-15T09:20:33+01:00",
        "parent": [
          {
            "reference": "Specimen/357337"
          }
        ],
        "collection": {
          "collectedDateTime": "2024-01-15T08:27:19+01:00",
          "quantity": {
            "value": 350,
            "unit": "MICL",
            "system": "urn:centraxx"
          }
        },
        "container": [
          {
            "identifier": [
              {
                "system": "urn:centraxx",
                "value": "NUM_AliContainer"
              }
            ],
            "capacity": {
              "value": 350,
              "unit": "MICL",
              "system": "urn:centraxx"
            },
            "specimenQuantity": {
              "value": 350,
              "unit": "MICL",
              "system": "urn:centraxx"
            }
          }
        ]
      },
      "request": {
        "method": "POST",
        "url": "Specimen/357338"
      }
    },
    {
      "fullUrl": "Specimen/357339",
      "resource": {
        "resourceType": "Specimen",
        "id": "357339",
        "extension": [
          {
            "url": "https://fhir.centraxx.de/extension/updateWithOverwrite",
            "valueBoolean": false
          },
          {
            "url": "https://fhir.centraxx.de/extension/sample/repositionDate",
            "valueDateTime": "2024-01-15T15:34:35.000+01:00"
          },
          {
            "url": "https://fhir.centraxx.de/extension/sample/sampleLocation",
            "extension": [
              {
                "url": "https://fhir.centraxx.de/extension/sample/sampleLocationPath",
                "valueString": "NUM --> Klinikum Würzburg --> N2 Tank POP -196°C"
              }
            ]
          },
          {
            "url": "https://fhir.centraxx.de/extension/sample/organizationUnit",
            "valueReference": {
              "identifier": {
                "value": "NUM_W_POP"
              }
            }
          },
          {
            "url": "https://fhir.centraxx.de/extension/sample/derivalDate",
            "valueDateTime": "2024-01-15T10:27:18.000+01:00"
          },
          {
            "url": "https://fhir.centraxx.de/extension/sampleCategory",
            "valueCoding": {
              "system": "urn:centraxx",
              "code": "DERIVED"
            }
          },
          {
            "url": "https://fhir.centraxx.de/extension/sample/concentration",
            "valueQuantity": {
              "value": 10,
              "unit": "XE06ML"
            }
          },
          {
            "url": "https://fhir.centraxx.de/extension/sprec",
            "extension": [
              {
                "url": "https://fhir.centraxx.de/extension/sprec/useSprec",
                "valueBoolean": false
              },
              {
                "url": "https://fhir.centraxx.de/extension/sprec/primarySampleContainer",
                "valueCoding": {
                  "system": "urn:centraxx",
                  "code": "CPT"
                }
              },
              {
                "url": "https://fhir.centraxx.de/extension/sprec/stockProcessing",
                "valueCoding": {
                  "system": "urn:centraxx",
                  "code": "NUM_BEGINN_ZENT"
                }
              },
              {
                "url": "https://fhir.centraxx.de/extension/sprec/secondProcessing",
                "valueCoding": {
                  "system": "urn:centraxx",
                  "code": "NUM_RT15min300gBremse"
                }
              }
            ]
          }
        ],
        "identifier": [
          {
            "type": {
              "coding": [
                {
                  "system": "urn:centraxx",
                  "code": "SAMPLEID"
                }
              ]
            },
            "value": "4080359581"
          }
        ],
        "status": "available",
        "type": {
          "coding": [
            {
              "system": "urn:centraxx",
              "code": "NUM_PBMC_C"
            }
          ]
        },
        "subject": {
          "identifier": {
            "type": {
              "coding": [
                {
                  "system": "urn:centraxx",
                  "code": "LIMSPSN"
                }
              ]
            },
            "value": "lims_852751117"
          }
        },
        "receivedTime": "2024-01-15T09:20:33+01:00",
        "parent": [
          {
            "reference": "Specimen/357337"
          }
        ],
        "collection": {
          "collectedDateTime": "2024-01-15T08:27:19+01:00",
          "quantity": {
            "value": 350,
            "unit": "MICL",
            "system": "urn:centraxx"
          }
        },
        "container": [
          {
            "identifier": [
              {
                "system": "urn:centraxx",
                "value": "NUM_AliContainer"
              }
            ],
            "capacity": {
              "value": 350,
              "unit": "MICL",
              "system": "urn:centraxx"
            },
            "specimenQuantity": {
              "value": 350,
              "unit": "MICL",
              "system": "urn:centraxx"
            }
          }
        ]
      },
      "request": {
        "method": "POST",
        "url": "Specimen/357339"
      }
    },
    {
      "fullUrl": "Specimen/366222",
      "resource": {
        "resourceType": "Specimen",
        "id": "366222",
        "extension": [
          {
            "url": "https://fhir.centraxx.de/extension/updateWithOverwrite",
            "valueBoolean": false
          },
          {
            "url": "https://fhir.centraxx.de/extension/sample/organizationUnit",
            "valueReference": {
              "identifier": {
                "value": "NUM_W_POP"
              }
            }
          },
          {
            "url": "https://fhir.centraxx.de/extension/sampleCategory",
            "valueCoding": {
              "system": "urn:centraxx",
              "code": "MASTER"
            }
          },
          {
            "url": "https://fhir.centraxx.de/extension/sprec",
            "extension": [
              {
                "url": "https://fhir.centraxx.de/extension/sprec/useSprec",
                "valueBoolean": false
              },
              {
                "url": "https://fhir.centraxx.de/extension/sprec/stockProcessing",
                "valueCoding": {
                  "system": "urn:centraxx",
                  "code": "Sprec-B"
                }
              },
              {
                "url": "https://fhir.centraxx.de/extension/sprec/stockProcessingDate",
                "valueDateTime": "2024-02-08T09:39:53.000+01:00"
              }
            ]
          }
        ],
        "identifier": [
          {
            "type": {
              "coding": [
                {
                  "system": "urn:centraxx",
                  "code": "EXTSAMPLEID"
                }
              ]
            },
            "value": "ST9909954821"
          },
          {
            "type": {
              "coding": [
                {
                  "system": "urn:centraxx",
                  "code": "SAMPLEID"
                }
              ]
            },
            "value": "1403280001"
          }
        ],
        "status": "unavailable",
        "type": {
          "coding": [
            {
              "system": "urn:centraxx",
              "code": "SER"
            }
          ]
        },
        "subject": {
          "identifier": {
            "type": {
              "coding": [
                {
                  "system": "urn:centraxx",
                  "code": "LIMSPSN"
                }
              ]
            },
            "value": "lims_827858138"
          }
        },
        "receivedTime": "2024-02-08T09:37:59+01:00",
        "collection": {
          "collectedDateTime": "2024-02-08T09:07:33+01:00",
          "quantity": {
            "value": 1,
            "unit": "PC",
            "system": "urn:centraxx"
          }
        },
        "container": [
          {
            "identifier": [
              {
                "system": "urn:centraxx",
                "value": "ORG"
              }
            ],
            "capacity": {
              "value": 1,
              "unit": "PC",
              "system": "urn:centraxx"
            },
            "specimenQuantity": {
              "value": 0,
              "unit": "PC",
              "system": "urn:centraxx"
            }
          }
        ]
      },
      "request": {
        "method": "POST",
        "url": "Specimen/366222"
      }
    },
    {
      "fullUrl": "Specimen/366223",
      "resource": {
        "resourceType": "Specimen",
        "id": "366223",
        "extension": [
          {
            "url": "https://fhir.centraxx.de/extension/updateWithOverwrite",
            "valueBoolean": false
          },
          {
            "url": "https://fhir.centraxx.de/extension/sample/organizationUnit",
            "valueReference": {
              "identifier": {
                "value": "NUM_W_POP"
              }
            }
          },
          {
            "url": "https://fhir.centraxx.de/extension/sampleCategory",
            "valueCoding": {
              "system": "urn:centraxx",
              "code": "MASTER"
            }
          },
          {
            "url": "https://fhir.centraxx.de/extension/sprec",
            "extension": [
              {
                "url": "https://fhir.centraxx.de/extension/sprec/useSprec",
                "valueBoolean": false
              },
              {
                "url": "https://fhir.centraxx.de/extension/sprec/stockProcessing",
                "valueCoding": {
                  "system": "urn:centraxx",
                  "code": "NUM_BEGINN_ZENT"
                }
              },
              {
                "url": "https://fhir.centraxx.de/extension/sprec/stockProcessingDate",
                "valueDateTime": "2024-02-08T09:52:36.000+01:00"
              }
            ]
          }
        ],
        "identifier": [
          {
            "type": {
              "coding": [
                {
                  "system": "urn:centraxx",
                  "code": "EXTSAMPLEID"
                }
              ]
            },
            "value": "ST9909954841"
          },
          {
            "type": {
              "coding": [
                {
                  "system": "urn:centraxx",
                  "code": "SAMPLEID"
                }
              ]
            },
            "value": "1403290004"
          }
        ],
        "status": "unavailable",
        "type": {
          "coding": [
            {
              "system": "urn:centraxx",
              "code": "URN"
            }
          ]
        },
        "subject": {
          "identifier": {
            "type": {
              "coding": [
                {
                  "system": "urn:centraxx",
                  "code": "LIMSPSN"
                }
              ]
            },
            "value": "lims_827858138"
          }
        },
        "receivedTime": "2024-02-08T09:37:55+01:00",
        "collection": {
          "collectedDateTime": "2024-02-08T09:00:31+01:00",
          "quantity": {
            "value": 1,
            "unit": "PC",
            "system": "urn:centraxx"
          }
        },
        "container": [
          {
            "identifier": [
              {
                "system": "urn:centraxx",
                "value": "ORG"
              }
            ],
            "capacity": {
              "value": 1,
              "unit": "PC",
              "system": "urn:centraxx"
            },
            "specimenQuantity": {
              "value": 0,
              "unit": "PC",
              "system": "urn:centraxx"
            }
          }
        ]
      },
      "request": {
        "method": "POST",
        "url": "Specimen/366223"
      }
    },
    {
      "fullUrl": "Specimen/366224",
      "resource": {
        "resourceType": "Specimen",
        "id": "366224",
        "extension": [
          {
            "url": "https://fhir.centraxx.de/extension/updateWithOverwrite",
            "valueBoolean": false
          },
          {
            "url": "https://fhir.centraxx.de/extension/sample/repositionDate",
            "valueDateTime": "2024-02-08T09:43:50.000+01:00"
          },
          {
            "url": "https://fhir.centraxx.de/extension/sample/sampleLocation",
            "extension": [
              {
                "url": "https://fhir.centraxx.de/extension/sample/sampleLocationPath",
                "valueString": "NUM --> Klinikum Würzburg --> Ultra-Tiefkühlschrank POP -80°C"
              }
            ]
          },
          {
            "url": "https://fhir.centraxx.de/extension/sample/organizationUnit",
            "valueReference": {
              "identifier": {
                "value": "NUM_W_POP"
              }
            }
          },
          {
            "url": "https://fhir.centraxx.de/extension/sampleCategory",
            "valueCoding": {
              "system": "urn:centraxx",
              "code": "MASTER"
            }
          },
          {
            "url": "https://fhir.centraxx.de/extension/sprec",
            "extension": [
              {
                "url": "https://fhir.centraxx.de/extension/sprec/useSprec",
                "valueBoolean": false
              }
            ]
          }
        ],
        "identifier": [
          {
            "type": {
              "coding": [
                {
                  "system": "urn:centraxx",
                  "code": "EXTSAMPLEID"
                }
              ]
            },
            "value": "ST9909954851"
          },
          {
            "type": {
              "coding": [
                {
                  "system": "urn:centraxx",
                  "code": "SAMPLEID"
                }
              ]
            },
            "value": "1403280797"
          }
        ],
        "status": "available",
        "type": {
          "coding": [
            {
              "system": "urn:centraxx",
              "code": "NUM_speichel"
            }
          ]
        },
        "subject": {
          "identifier": {
            "type": {
              "coding": [
                {
                  "system": "urn:centraxx",
                  "code": "LIMSPSN"
                }
              ]
            },
            "value": "lims_827858138"
          }
        },
        "receivedTime": "2024-02-08T09:37:25+01:00",
        "collection": {
          "collectedDateTime": "2024-02-08T09:07:06+01:00",
          "quantity": {
            "value": 1,
            "unit": "PC",
            "system": "urn:centraxx"
          }
        },
        "container": [
          {
            "identifier": [
              {
                "system": "urn:centraxx",
                "value": "ORG"
              }
            ],
            "capacity": {
              "value": 1,
              "unit": "PC",
              "system": "urn:centraxx"
            },
            "specimenQuantity": {
              "value": 1,
              "unit": "PC",
              "system": "urn:centraxx"
            }
          }
        ]
      },
      "request": {
        "method": "POST",
        "url": "Specimen/366224"
      }
    },
    {
      "fullUrl": "Specimen/366225",
      "resource": {
        "resourceType": "Specimen",
        "id": "366225",
        "extension": [
          {
            "url": "https://fhir.centraxx.de/extension/updateWithOverwrite",
            "valueBoolean": false
          },
          {
            "url": "https://fhir.centraxx.de/extension/sample/organizationUnit",
            "valueReference": {
              "identifier": {
                "value": "NUM_W_POP"
              }
            }
          },
          {
            "url": "https://fhir.centraxx.de/extension/sampleCategory",
            "valueCoding": {
              "system": "urn:centraxx",
              "code": "MASTER"
            }
          },
          {
            "url": "https://fhir.centraxx.de/extension/sprec",
            "extension": [
              {
                "url": "https://fhir.centraxx.de/extension/sprec/useSprec",
                "valueBoolean": false
              },
              {
                "url": "https://fhir.centraxx.de/extension/sprec/stockProcessing",
                "valueCoding": {
                  "system": "urn:centraxx",
                  "code": "Sprec-B"
                }
              },
              {
                "url": "https://fhir.centraxx.de/extension/sprec/stockProcessingDate",
                "valueDateTime": "2024-02-08T09:40:17.000+01:00"
              }
            ]
          }
        ],
        "identifier": [
          {
            "type": {
              "coding": [
                {
                  "system": "urn:centraxx",
                  "code": "EXTSAMPLEID"
                }
              ]
            },
            "value": "ST9909954861"
          },
          {
            "type": {
              "coding": [
                {
                  "system": "urn:centraxx",
                  "code": "SAMPLEID"
                }
              ]
            },
            "value": "1403280403"
          }
        ],
        "status": "unavailable",
        "type": {
          "coding": [
            {
              "system": "urn:centraxx",
              "code": "CIT"
            }
          ]
        },
        "subject": {
          "identifier": {
            "type": {
              "coding": [
                {
                  "system": "urn:centraxx",
                  "code": "LIMSPSN"
                }
              ]
            },
            "value": "lims_827858138"
          }
        },
        "receivedTime": "2024-02-08T09:37:53+01:00",
        "collection": {
          "collectedDateTime": "2024-02-08T09:07:21+01:00",
          "quantity": {
            "value": 1,
            "unit": "PC",
            "system": "urn:centraxx"
          }
        },
        "container": [
          {
            "identifier": [
              {
                "system": "urn:centraxx",
                "value": "ORG"
              }
            ],
            "capacity": {
              "value": 1,
              "unit": "PC",
              "system": "urn:centraxx"
            },
            "specimenQuantity": {
              "value": 0,
              "unit": "PC",
              "system": "urn:centraxx"
            }
          }
        ]
      },
      "request": {
        "method": "POST",
        "url": "Specimen/366225"
      }
    },
    {
      "fullUrl": "Specimen/366226",
      "resource": {
        "resourceType": "Specimen",
        "id": "366226",
        "extension": [
          {
            "url": "https://fhir.centraxx.de/extension/updateWithOverwrite",
            "valueBoolean": false
          },
          {
            "url": "https://fhir.centraxx.de/extension/sample/organizationUnit",
            "valueReference": {
              "identifier": {
                "value": "NUM_W_POP"
              }
            }
          },
          {
            "url": "https://fhir.centraxx.de/extension/sampleCategory",
            "valueCoding": {
              "system": "urn:centraxx",
              "code": "MASTER"
            }
          },
          {
            "url": "https://fhir.centraxx.de/extension/sprec",
            "extension": [
              {
                "url": "https://fhir.centraxx.de/extension/sprec/useSprec",
                "valueBoolean": false
              },
              {
                "url": "https://fhir.centraxx.de/extension/sprec/stockProcessing",
                "valueCoding": {
                  "system": "urn:centraxx",
                  "code": "Sprec-B"
                }
              },
              {
                "url": "https://fhir.centraxx.de/extension/sprec/stockProcessingDate",
                "valueDateTime": "2024-02-08T09:40:31.000+01:00"
              }
            ]
          }
        ],
        "identifier": [
          {
            "type": {
              "coding": [
                {
                  "system": "urn:centraxx",
                  "code": "EXTSAMPLEID"
                }
              ]
            },
            "value": "ST9909954881"
          },
          {
            "type": {
              "coding": [
                {
                  "system": "urn:centraxx",
                  "code": "SAMPLEID"
                }
              ]
            },
            "value": "1403280107"
          }
        ],
        "status": "unavailable",
        "type": {
          "coding": [
            {
              "system": "urn:centraxx",
              "code": "EDTAWB"
            }
          ]
        },
        "subject": {
          "identifier": {
            "type": {
              "coding": [
                {
                  "system": "urn:centraxx",
                  "code": "LIMSPSN"
                }
              ]
            },
            "value": "lims_827858138"
          }
        },
        "receivedTime": "2024-02-08T09:37:43+01:00",
        "collection": {
          "collectedDateTime": "2024-02-08T09:07:49+01:00",
          "quantity": {
            "value": 1,
            "unit": "PC",
            "system": "urn:centraxx"
          }
        },
        "container": [
          {
            "identifier": [
              {
                "system": "urn:centraxx",
                "value": "ORG"
              }
            ],
            "capacity": {
              "value": 1,
              "unit": "PC",
              "system": "urn:centraxx"
            },
            "specimenQuantity": {
              "value": 0,
              "unit": "PC",
              "system": "urn:centraxx"
            }
          }
        ]
      },
      "request": {
        "method": "POST",
        "url": "Specimen/366226"
      }
    }
  ]
}
