{"resourceType": "Bundle", "type": "transaction", "entry": [{"fullUrl": "Specimen/358014", "resource": {"resourceType": "Specimen", "id": "358014", "extension": [{"url": "https://fhir.centraxx.de/extension/updateWithOverwrite", "valueBoolean": false}, {"url": "https://fhir.centraxx.de/extension/sample/organizationUnit", "valueReference": {"identifier": {"value": "NUM_W_POP"}}}, {"url": "https://fhir.centraxx.de/extension/sampleCategory", "valueCoding": {"system": "urn:centraxx", "code": "ALIQUOTGROUP"}}, {"url": "https://fhir.centraxx.de/extension/sprec", "extension": [{"url": "https://fhir.centraxx.de/extension/sprec/useSprec", "valueBoolean": false}]}], "status": "unavailable", "type": {"coding": [{"system": "urn:centraxx", "code": "NUM_urinf"}]}, "subject": {"identifier": {"type": {"coding": [{"system": "urn:centraxx", "code": "LIMSPSN"}]}, "value": "lims_212336720"}}, "receivedTime": "2024-01-16T09:16:45+01:00", "parent": [{"identifier": {"type": {"coding": [{"code": "SAMPLEID"}]}, "value": "1401000004"}}], "collection": {"collectedDateTime": "2024-01-16T08:35:45+01:00", "quantity": {"system": "urn:centraxx"}}, "container": [{"specimenQuantity": {"system": "urn:centraxx"}}]}, "request": {"method": "POST", "url": "Specimen/358014"}}, {"fullUrl": "Specimen/358016", "resource": {"resourceType": "Specimen", "id": "358016", "extension": [{"url": "https://fhir.centraxx.de/extension/updateWithOverwrite", "valueBoolean": false}, {"url": "https://fhir.centraxx.de/extension/sample/organizationUnit", "valueReference": {"identifier": {"value": "NUM_W_POP"}}}, {"url": "https://fhir.centraxx.de/extension/sampleCategory", "valueCoding": {"system": "urn:centraxx", "code": "ALIQUOTGROUP"}}, {"url": "https://fhir.centraxx.de/extension/sprec", "extension": [{"url": "https://fhir.centraxx.de/extension/sprec/useSprec", "valueBoolean": false}]}], "status": "unavailable", "type": {"coding": [{"system": "urn:centraxx", "code": "NUM_urinf"}]}, "subject": {"identifier": {"type": {"coding": [{"system": "urn:centraxx", "code": "LIMSPSN"}]}, "value": "lims_212336720"}}, "receivedTime": "2024-01-16T09:16:45+01:00", "parent": [{"identifier": {"type": {"coding": [{"code": "SAMPLEID"}]}, "value": "1401000004"}}], "collection": {"collectedDateTime": "2024-01-16T08:35:45+01:00", "quantity": {"system": "urn:centraxx"}}, "container": [{"specimenQuantity": {"system": "urn:centraxx"}}]}, "request": {"method": "POST", "url": "Specimen/358016"}}, {"fullUrl": "Specimen/358018", "resource": {"resourceType": "Specimen", "id": "358018", "extension": [{"url": "https://fhir.centraxx.de/extension/updateWithOverwrite", "valueBoolean": false}, {"url": "https://fhir.centraxx.de/extension/sample/organizationUnit", "valueReference": {"identifier": {"value": "NUM_W_POP"}}}, {"url": "https://fhir.centraxx.de/extension/sampleCategory", "valueCoding": {"system": "urn:centraxx", "code": "ALIQUOTGROUP"}}, {"url": "https://fhir.centraxx.de/extension/sprec", "extension": [{"url": "https://fhir.centraxx.de/extension/sprec/useSprec", "valueBoolean": false}]}], "status": "unavailable", "type": {"coding": [{"system": "urn:centraxx", "code": "NUM_urinf"}]}, "subject": {"identifier": {"type": {"coding": [{"system": "urn:centraxx", "code": "LIMSPSN"}]}, "value": "lims_212336720"}}, "receivedTime": "2024-01-16T09:16:45+01:00", "parent": [{"identifier": {"type": {"coding": [{"code": "SAMPLEID"}]}, "value": "1401000004"}}], "collection": {"collectedDateTime": "2024-01-16T08:35:45+01:00", "quantity": {"system": "urn:centraxx"}}, "container": [{"specimenQuantity": {"system": "urn:centraxx"}}]}, "request": {"method": "POST", "url": "Specimen/358018"}}, {"fullUrl": "Specimen/358020", "resource": {"resourceType": "Specimen", "id": "358020", "extension": [{"url": "https://fhir.centraxx.de/extension/updateWithOverwrite", "valueBoolean": false}, {"url": "https://fhir.centraxx.de/extension/sample/organizationUnit", "valueReference": {"identifier": {"value": "NUM_W_POP"}}}, {"url": "https://fhir.centraxx.de/extension/sampleCategory", "valueCoding": {"system": "urn:centraxx", "code": "ALIQUOTGROUP"}}, {"url": "https://fhir.centraxx.de/extension/sprec", "extension": [{"url": "https://fhir.centraxx.de/extension/sprec/useSprec", "valueBoolean": false}]}], "status": "unavailable", "type": {"coding": [{"system": "urn:centraxx", "code": "NUM_urinf"}]}, "subject": {"identifier": {"type": {"coding": [{"system": "urn:centraxx", "code": "LIMSPSN"}]}, "value": "lims_212336720"}}, "receivedTime": "2024-01-16T09:16:45+01:00", "parent": [{"identifier": {"type": {"coding": [{"code": "SAMPLEID"}]}, "value": "1401000004"}}], "collection": {"collectedDateTime": "2024-01-16T08:35:45+01:00", "quantity": {"system": "urn:centraxx"}}, "container": [{"specimenQuantity": {"system": "urn:centraxx"}}]}, "request": {"method": "POST", "url": "Specimen/358020"}}, {"fullUrl": "Specimen/358022", "resource": {"resourceType": "Specimen", "id": "358022", "extension": [{"url": "https://fhir.centraxx.de/extension/updateWithOverwrite", "valueBoolean": false}, {"url": "https://fhir.centraxx.de/extension/sample/organizationUnit", "valueReference": {"identifier": {"value": "NUM_W_POP"}}}, {"url": "https://fhir.centraxx.de/extension/sampleCategory", "valueCoding": {"system": "urn:centraxx", "code": "ALIQUOTGROUP"}}, {"url": "https://fhir.centraxx.de/extension/sprec", "extension": [{"url": "https://fhir.centraxx.de/extension/sprec/useSprec", "valueBoolean": false}]}], "status": "unavailable", "type": {"coding": [{"system": "urn:centraxx", "code": "NUM_urinf"}]}, "subject": {"identifier": {"type": {"coding": [{"system": "urn:centraxx", "code": "LIMSPSN"}]}, "value": "lims_212336720"}}, "receivedTime": "2024-01-16T09:16:45+01:00", "parent": [{"identifier": {"type": {"coding": [{"code": "SAMPLEID"}]}, "value": "1401000004"}}], "collection": {"collectedDateTime": "2024-01-16T08:35:45+01:00", "quantity": {"system": "urn:centraxx"}}, "container": [{"specimenQuantity": {"system": "urn:centraxx"}}]}, "request": {"method": "POST", "url": "Specimen/358022"}}, {"fullUrl": "Specimen/358024", "resource": {"resourceType": "Specimen", "id": "358024", "extension": [{"url": "https://fhir.centraxx.de/extension/updateWithOverwrite", "valueBoolean": false}, {"url": "https://fhir.centraxx.de/extension/sample/organizationUnit", "valueReference": {"identifier": {"value": "NUM_W_POP"}}}, {"url": "https://fhir.centraxx.de/extension/sampleCategory", "valueCoding": {"system": "urn:centraxx", "code": "ALIQUOTGROUP"}}, {"url": "https://fhir.centraxx.de/extension/sprec", "extension": [{"url": "https://fhir.centraxx.de/extension/sprec/useSprec", "valueBoolean": false}]}], "status": "unavailable", "type": {"coding": [{"system": "urn:centraxx", "code": "NUM_urins"}]}, "subject": {"identifier": {"type": {"coding": [{"system": "urn:centraxx", "code": "LIMSPSN"}]}, "value": "lims_212336720"}}, "receivedTime": "2024-01-16T09:16:45+01:00", "parent": [{"identifier": {"type": {"coding": [{"code": "SAMPLEID"}]}, "value": "1401000004"}}], "collection": {"collectedDateTime": "2024-01-16T08:35:45+01:00", "quantity": {"system": "urn:centraxx"}}, "container": [{"specimenQuantity": {"system": "urn:centraxx"}}]}, "request": {"method": "POST", "url": "Specimen/358024"}}, {"fullUrl": "Specimen/358026", "resource": {"resourceType": "Specimen", "id": "358026", "extension": [{"url": "https://fhir.centraxx.de/extension/updateWithOverwrite", "valueBoolean": false}, {"url": "https://fhir.centraxx.de/extension/sample/organizationUnit", "valueReference": {"identifier": {"value": "NUM_W_POP"}}}, {"url": "https://fhir.centraxx.de/extension/sampleCategory", "valueCoding": {"system": "urn:centraxx", "code": "ALIQUOTGROUP"}}, {"url": "https://fhir.centraxx.de/extension/sprec", "extension": [{"url": "https://fhir.centraxx.de/extension/sprec/useSprec", "valueBoolean": false}]}], "status": "unavailable", "type": {"coding": [{"system": "urn:centraxx", "code": "NUM_urins"}]}, "subject": {"identifier": {"type": {"coding": [{"system": "urn:centraxx", "code": "LIMSPSN"}]}, "value": "lims_212336720"}}, "receivedTime": "2024-01-16T09:16:45+01:00", "parent": [{"identifier": {"type": {"coding": [{"code": "SAMPLEID"}]}, "value": "1401000004"}}], "collection": {"collectedDateTime": "2024-01-16T08:35:45+01:00", "quantity": {"system": "urn:centraxx"}}, "container": [{"specimenQuantity": {"system": "urn:centraxx"}}]}, "request": {"method": "POST", "url": "Specimen/358026"}}, {"fullUrl": "Specimen/358028", "resource": {"resourceType": "Specimen", "id": "358028", "extension": [{"url": "https://fhir.centraxx.de/extension/updateWithOverwrite", "valueBoolean": false}, {"url": "https://fhir.centraxx.de/extension/sample/organizationUnit", "valueReference": {"identifier": {"value": "NUM_W_POP"}}}, {"url": "https://fhir.centraxx.de/extension/sampleCategory", "valueCoding": {"system": "urn:centraxx", "code": "ALIQUOTGROUP"}}, {"url": "https://fhir.centraxx.de/extension/sprec", "extension": [{"url": "https://fhir.centraxx.de/extension/sprec/useSprec", "valueBoolean": false}]}], "status": "unavailable", "type": {"coding": [{"system": "urn:centraxx", "code": "SER"}]}, "subject": {"identifier": {"type": {"coding": [{"system": "urn:centraxx", "code": "LIMSPSN"}]}, "value": "lims_212336720"}}, "receivedTime": "2024-01-16T09:17:08+01:00", "parent": [{"identifier": {"type": {"coding": [{"code": "SAMPLEID"}]}, "value": "1400990001"}}], "collection": {"collectedDateTime": "2024-01-16T08:50:15+01:00", "quantity": {"system": "urn:centraxx"}}, "container": [{"specimenQuantity": {"system": "urn:centraxx"}}]}, "request": {"method": "POST", "url": "Specimen/358028"}}, {"fullUrl": "Specimen/358041", "resource": {"resourceType": "Specimen", "id": "358041", "extension": [{"url": "https://fhir.centraxx.de/extension/updateWithOverwrite", "valueBoolean": false}, {"url": "https://fhir.centraxx.de/extension/sample/organizationUnit", "valueReference": {"identifier": {"value": "NUM_W_POP"}}}, {"url": "https://fhir.centraxx.de/extension/sampleCategory", "valueCoding": {"system": "urn:centraxx", "code": "ALIQUOTGROUP"}}, {"url": "https://fhir.centraxx.de/extension/sprec", "extension": [{"url": "https://fhir.centraxx.de/extension/sprec/useSprec", "valueBoolean": false}, {"url": "https://fhir.centraxx.de/extension/sprec/primarySampleContainer", "valueCoding": {"system": "urn:centraxx", "code": "CPT"}}, {"url": "https://fhir.centraxx.de/extension/sprec/stockProcessing", "valueCoding": {"system": "urn:centraxx", "code": "NUM_BEGINN_ZENT"}}, {"url": "https://fhir.centraxx.de/extension/sprec/secondProcessing", "valueCoding": {"system": "urn:centraxx", "code": "NUM_RT15min300gBremse"}}]}], "status": "unavailable", "type": {"coding": [{"system": "urn:centraxx", "code": "NUM_PBMC_C"}]}, "subject": {"identifier": {"type": {"coding": [{"system": "urn:centraxx", "code": "LIMSPSN"}]}, "value": "lims_212336720"}}, "receivedTime": "2024-01-16T09:15:44+01:00", "parent": [{"identifier": {"type": {"coding": [{"code": "SAMPLEID"}]}, "value": "1400990699"}}], "collection": {"collectedDateTime": "2024-01-16T08:50:26+01:00", "quantity": {"system": "urn:centraxx"}}, "container": [{"specimenQuantity": {"system": "urn:centraxx"}}]}, "request": {"method": "POST", "url": "Specimen/358041"}}, {"fullUrl": "Specimen/357958", "resource": {"resourceType": "Specimen", "id": "357958", "extension": [{"url": "https://fhir.centraxx.de/extension/updateWithOverwrite", "valueBoolean": false}, {"url": "https://fhir.centraxx.de/extension/sample/repositionDate", "valueDateTime": "2024-01-16T09:52:19.000+01:00"}, {"url": "https://fhir.centraxx.de/extension/sample/sampleLocation", "extension": [{"url": "https://fhir.centraxx.de/extension/sample/sampleLocationPath", "valueString": "NUM --> Klinikum W\u00fcrzburg --> Ultra-Tiefk\u00fchlschrank POP -80\u00b0C"}]}, {"url": "https://fhir.centraxx.de/extension/sample/organizationUnit", "valueReference": {"identifier": {"value": "NUM_W_POP"}}}, {"url": "https://fhir.centraxx.de/extension/sample/derivalDate", "valueDateTime": "2024-01-16T09:38:22.000+01:00"}, {"url": "https://fhir.centraxx.de/extension/sampleCategory", "valueCoding": {"system": "urn:centraxx", "code": "DERIVED"}}, {"url": "https://fhir.centraxx.de/extension/sprec", "extension": [{"url": "https://fhir.centraxx.de/extension/sprec/useSprec", "valueBoolean": false}, {"url": "https://fhir.centraxx.de/extension/sprec/stockProcessing", "valueCoding": {"system": "urn:centraxx", "code": "Sprec-B"}}]}], "identifier": [{"type": {"coding": [{"system": "urn:centraxx", "code": "SAMPLEID"}]}, "value": "4080426687"}], "status": "available", "type": {"coding": [{"system": "urn:centraxx", "code": "SER"}]}, "subject": {"identifier": {"type": {"coding": [{"system": "urn:centraxx", "code": "LIMSPSN"}]}, "value": "lims_212336720"}}, "parent": [{"reference": "Specimen/357957"}], "collection": {"collectedDateTime": "2024-01-16T08:50:15+01:00", "quantity": {"value": 350, "unit": "MICL", "system": "urn:centraxx"}}, "container": [{"identifier": [{"system": "urn:centraxx", "value": "NUM_AliContainer"}], "capacity": {"value": 350, "unit": "MICL", "system": "urn:centraxx"}, "specimenQuantity": {"value": 350, "unit": "MICL", "system": "urn:centraxx"}}]}, "request": {"method": "POST", "url": "Specimen/357958"}}, {"fullUrl": "Specimen/357959", "resource": {"resourceType": "Specimen", "id": "357959", "extension": [{"url": "https://fhir.centraxx.de/extension/updateWithOverwrite", "valueBoolean": false}, {"url": "https://fhir.centraxx.de/extension/sample/repositionDate", "valueDateTime": "2024-01-16T09:52:19.000+01:00"}, {"url": "https://fhir.centraxx.de/extension/sample/sampleLocation", "extension": [{"url": "https://fhir.centraxx.de/extension/sample/sampleLocationPath", "valueString": "NUM --> Klinikum W\u00fcrzburg --> Ultra-Tiefk\u00fchlschrank POP -80\u00b0C"}]}, {"url": "https://fhir.centraxx.de/extension/sample/organizationUnit", "valueReference": {"identifier": {"value": "NUM_W_POP"}}}, {"url": "https://fhir.centraxx.de/extension/sample/derivalDate", "valueDateTime": "2024-01-16T09:38:42.000+01:00"}, {"url": "https://fhir.centraxx.de/extension/sampleCategory", "valueCoding": {"system": "urn:centraxx", "code": "DERIVED"}}, {"url": "https://fhir.centraxx.de/extension/sprec", "extension": [{"url": "https://fhir.centraxx.de/extension/sprec/useSprec", "valueBoolean": false}, {"url": "https://fhir.centraxx.de/extension/sprec/stockProcessing", "valueCoding": {"system": "urn:centraxx", "code": "Sprec-B"}}]}], "identifier": [{"type": {"coding": [{"system": "urn:centraxx", "code": "SAMPLEID"}]}, "value": "4080426683"}], "status": "available", "type": {"coding": [{"system": "urn:centraxx", "code": "SER"}]}, "subject": {"identifier": {"type": {"coding": [{"system": "urn:centraxx", "code": "LIMSPSN"}]}, "value": "lims_212336720"}}, "parent": [{"reference": "Specimen/357957"}], "collection": {"collectedDateTime": "2024-01-16T08:50:15+01:00", "quantity": {"value": 350, "unit": "MICL", "system": "urn:centraxx"}}, "container": [{"identifier": [{"system": "urn:centraxx", "value": "NUM_AliContainer"}], "capacity": {"value": 350, "unit": "MICL", "system": "urn:centraxx"}, "specimenQuantity": {"value": 350, "unit": "MICL", "system": "urn:centraxx"}}]}, "request": {"method": "POST", "url": "Specimen/357959"}}, {"fullUrl": "Specimen/357960", "resource": {"resourceType": "Specimen", "id": "357960", "extension": [{"url": "https://fhir.centraxx.de/extension/updateWithOverwrite", "valueBoolean": false}, {"url": "https://fhir.centraxx.de/extension/sample/repositionDate", "valueDateTime": "2024-01-16T09:52:19.000+01:00"}, {"url": "https://fhir.centraxx.de/extension/sample/sampleLocation", "extension": [{"url": "https://fhir.centraxx.de/extension/sample/sampleLocationPath", "valueString": "NUM --> Klinikum W\u00fcrzburg --> Ultra-Tiefk\u00fchlschrank POP -80\u00b0C"}]}, {"url": "https://fhir.centraxx.de/extension/sample/organizationUnit", "valueReference": {"identifier": {"value": "NUM_W_POP"}}}, {"url": "https://fhir.centraxx.de/extension/sample/derivalDate", "valueDateTime": "2024-01-16T09:39:02.000+01:00"}, {"url": "https://fhir.centraxx.de/extension/sampleCategory", "valueCoding": {"system": "urn:centraxx", "code": "DERIVED"}}, {"url": "https://fhir.centraxx.de/extension/sprec", "extension": [{"url": "https://fhir.centraxx.de/extension/sprec/useSprec", "valueBoolean": false}, {"url": "https://fhir.centraxx.de/extension/sprec/stockProcessing", "valueCoding": {"system": "urn:centraxx", "code": "Sprec-B"}}]}], "identifier": [{"type": {"coding": [{"system": "urn:centraxx", "code": "SAMPLEID"}]}, "value": "4080426684"}], "status": "available", "type": {"coding": [{"system": "urn:centraxx", "code": "SER"}]}, "subject": {"identifier": {"type": {"coding": [{"system": "urn:centraxx", "code": "LIMSPSN"}]}, "value": "lims_212336720"}}, "parent": [{"reference": "Specimen/357957"}], "collection": {"collectedDateTime": "2024-01-16T08:50:15+01:00", "quantity": {"value": 350, "unit": "MICL", "system": "urn:centraxx"}}, "container": [{"identifier": [{"system": "urn:centraxx", "value": "NUM_AliContainer"}], "capacity": {"value": 350, "unit": "MICL", "system": "urn:centraxx"}, "specimenQuantity": {"value": 350, "unit": "MICL", "system": "urn:centraxx"}}]}, "request": {"method": "POST", "url": "Specimen/357960"}}, {"fullUrl": "Specimen/357961", "resource": {"resourceType": "Specimen", "id": "357961", "extension": [{"url": "https://fhir.centraxx.de/extension/updateWithOverwrite", "valueBoolean": false}, {"url": "https://fhir.centraxx.de/extension/sample/repositionDate", "valueDateTime": "2024-01-16T09:52:19.000+01:00"}, {"url": "https://fhir.centraxx.de/extension/sample/sampleLocation", "extension": [{"url": "https://fhir.centraxx.de/extension/sample/sampleLocationPath", "valueString": "NUM --> Klinikum W\u00fcrzburg --> Ultra-Tiefk\u00fchlschrank POP -80\u00b0C"}]}, {"url": "https://fhir.centraxx.de/extension/sample/organizationUnit", "valueReference": {"identifier": {"value": "NUM_W_POP"}}}, {"url": "https://fhir.centraxx.de/extension/sample/derivalDate", "valueDateTime": "2024-01-16T09:39:22.000+01:00"}, {"url": "https://fhir.centraxx.de/extension/sampleCategory", "valueCoding": {"system": "urn:centraxx", "code": "DERIVED"}}, {"url": "https://fhir.centraxx.de/extension/sprec", "extension": [{"url": "https://fhir.centraxx.de/extension/sprec/useSprec", "valueBoolean": false}, {"url": "https://fhir.centraxx.de/extension/sprec/stockProcessing", "valueCoding": {"system": "urn:centraxx", "code": "Sprec-B"}}]}], "identifier": [{"type": {"coding": [{"system": "urn:centraxx", "code": "SAMPLEID"}]}, "value": "4080426685"}], "status": "available", "type": {"coding": [{"system": "urn:centraxx", "code": "SER"}]}, "subject": {"identifier": {"type": {"coding": [{"system": "urn:centraxx", "code": "LIMSPSN"}]}, "value": "lims_212336720"}}, "parent": [{"reference": "Specimen/357957"}], "collection": {"collectedDateTime": "2024-01-16T08:50:15+01:00", "quantity": {"value": 350, "unit": "MICL", "system": "urn:centraxx"}}, "container": [{"identifier": [{"system": "urn:centraxx", "value": "NUM_AliContainer"}], "capacity": {"value": 350, "unit": "MICL", "system": "urn:centraxx"}, "specimenQuantity": {"value": 350, "unit": "MICL", "system": "urn:centraxx"}}]}, "request": {"method": "POST", "url": "Specimen/357961"}}, {"fullUrl": "Specimen/357981", "resource": {"resourceType": "Specimen", "id": "357981", "extension": [{"url": "https://fhir.centraxx.de/extension/updateWithOverwrite", "valueBoolean": false}, {"url": "https://fhir.centraxx.de/extension/sample/repositionDate", "valueDateTime": "2024-01-16T09:52:20.000+01:00"}, {"url": "https://fhir.centraxx.de/extension/sample/sampleLocation", "extension": [{"url": "https://fhir.centraxx.de/extension/sample/sampleLocationPath", "valueString": "NUM --> Klinikum W\u00fcrzburg --> Ultra-Tiefk\u00fchlschrank POP -80\u00b0C"}]}, {"url": "https://fhir.centraxx.de/extension/sample/organizationUnit", "valueReference": {"identifier": {"value": "NUM_W_POP"}}}, {"url": "https://fhir.centraxx.de/extension/sample/derivalDate", "valueDateTime": "2024-01-16T09:45:19.000+01:00"}, {"url": "https://fhir.centraxx.de/extension/sampleCategory", "valueCoding": {"system": "urn:centraxx", "code": "DERIVED"}}, {"url": "https://fhir.centraxx.de/extension/sprec", "extension": [{"url": "https://fhir.centraxx.de/extension/sprec/useSprec", "valueBoolean": false}, {"url": "https://fhir.centraxx.de/extension/sprec/stockProcessing", "valueCoding": {"system": "urn:centraxx", "code": "Sprec-B"}}]}], "identifier": [{"type": {"coding": [{"system": "urn:centraxx", "code": "SAMPLEID"}]}, "value": "4080426723"}], "status": "available", "type": {"coding": [{"system": "urn:centraxx", "code": "CIT"}]}, "subject": {"identifier": {"type": {"coding": [{"system": "urn:centraxx", "code": "LIMSPSN"}]}, "value": "lims_212336720"}}, "parent": [{"reference": "Specimen/357980"}], "collection": {"collectedDateTime": "2024-01-16T08:50:44+01:00", "quantity": {"value": 350, "unit": "MICL", "system": "urn:centraxx"}}, "container": [{"identifier": [{"system": "urn:centraxx", "value": "NUM_AliContainer"}], "capacity": {"value": 350, "unit": "MICL", "system": "urn:centraxx"}, "specimenQuantity": {"value": 350, "unit": "MICL", "system": "urn:centraxx"}}]}, "request": {"method": "POST", "url": "Specimen/357981"}}, {"fullUrl": "Specimen/357983", "resource": {"resourceType": "Specimen", "id": "357983", "extension": [{"url": "https://fhir.centraxx.de/extension/updateWithOverwrite", "valueBoolean": false}, {"url": "https://fhir.centraxx.de/extension/sample/repositionDate", "valueDateTime": "2024-01-16T09:52:20.000+01:00"}, {"url": "https://fhir.centraxx.de/extension/sample/sampleLocation", "extension": [{"url": "https://fhir.centraxx.de/extension/sample/sampleLocationPath", "valueString": "NUM --> Klinikum W\u00fcrzburg --> Ultra-Tiefk\u00fchlschrank POP -80\u00b0C"}]}, {"url": "https://fhir.centraxx.de/extension/sample/organizationUnit", "valueReference": {"identifier": {"value": "NUM_W_POP"}}}, {"url": "https://fhir.centraxx.de/extension/sample/derivalDate", "valueDateTime": "2024-01-16T09:45:20.000+01:00"}, {"url": "https://fhir.centraxx.de/extension/sampleCategory", "valueCoding": {"system": "urn:centraxx", "code": "DERIVED"}}, {"url": "https://fhir.centraxx.de/extension/sprec", "extension": [{"url": "https://fhir.centraxx.de/extension/sprec/useSprec", "valueBoolean": false}, {"url": "https://fhir.centraxx.de/extension/sprec/stockProcessing", "valueCoding": {"system": "urn:centraxx", "code": "Sprec-B"}}]}], "identifier": [{"type": {"coding": [{"system": "urn:centraxx", "code": "SAMPLEID"}]}, "value": "4080426698"}], "status": "available", "type": {"coding": [{"system": "urn:centraxx", "code": "CIT"}]}, "subject": {"identifier": {"type": {"coding": [{"system": "urn:centraxx", "code": "LIMSPSN"}]}, "value": "lims_212336720"}}, "parent": [{"reference": "Specimen/357982"}], "collection": {"collectedDateTime": "2024-01-16T08:50:44+01:00", "quantity": {"value": 350, "unit": "MICL", "system": "urn:centraxx"}}, "container": [{"identifier": [{"system": "urn:centraxx", "value": "NUM_AliContainer"}], "capacity": {"value": 350, "unit": "MICL", "system": "urn:centraxx"}, "specimenQuantity": {"value": 350, "unit": "MICL", "system": "urn:centraxx"}}]}, "request": {"method": "POST", "url": "Specimen/357983"}}, {"fullUrl": "Specimen/357985", "resource": {"resourceType": "Specimen", "id": "357985", "extension": [{"url": "https://fhir.centraxx.de/extension/updateWithOverwrite", "valueBoolean": false}, {"url": "https://fhir.centraxx.de/extension/sample/repositionDate", "valueDateTime": "2024-01-16T09:52:20.000+01:00"}, {"url": "https://fhir.centraxx.de/extension/sample/sampleLocation", "extension": [{"url": "https://fhir.centraxx.de/extension/sample/sampleLocationPath", "valueString": "NUM --> Klinikum W\u00fcrzburg --> Ultra-Tiefk\u00fchlschrank POP -80\u00b0C"}]}, {"url": "https://fhir.centraxx.de/extension/sample/organizationUnit", "valueReference": {"identifier": {"value": "NUM_W_POP"}}}, {"url": "https://fhir.centraxx.de/extension/sample/derivalDate", "valueDateTime": "2024-01-16T09:45:24.000+01:00"}, {"url": "https://fhir.centraxx.de/extension/sampleCategory", "valueCoding": {"system": "urn:centraxx", "code": "DERIVED"}}, {"url": "https://fhir.centraxx.de/extension/sprec", "extension": [{"url": "https://fhir.centraxx.de/extension/sprec/useSprec", "valueBoolean": false}, {"url": "https://fhir.centraxx.de/extension/sprec/stockProcessing", "valueCoding": {"system": "urn:centraxx", "code": "Sprec-B"}}]}], "identifier": [{"type": {"coding": [{"system": "urn:centraxx", "code": "SAMPLEID"}]}, "value": "4080426710"}], "status": "available", "type": {"coding": [{"system": "urn:centraxx", "code": "CIT"}]}, "subject": {"identifier": {"type": {"coding": [{"system": "urn:centraxx", "code": "LIMSPSN"}]}, "value": "lims_212336720"}}, "parent": [{"reference": "Specimen/357984"}], "collection": {"collectedDateTime": "2024-01-16T08:50:44+01:00", "quantity": {"value": 350, "unit": "MICL", "system": "urn:centraxx"}}, "container": [{"identifier": [{"system": "urn:centraxx", "value": "NUM_AliContainer"}], "capacity": {"value": 350, "unit": "MICL", "system": "urn:centraxx"}, "specimenQuantity": {"value": 350, "unit": "MICL", "system": "urn:centraxx"}}]}, "request": {"method": "POST", "url": "Specimen/357985"}}, {"fullUrl": "Specimen/357987", "resource": {"resourceType": "Specimen", "id": "357987", "extension": [{"url": "https://fhir.centraxx.de/extension/updateWithOverwrite", "valueBoolean": false}, {"url": "https://fhir.centraxx.de/extension/sample/repositionDate", "valueDateTime": "2024-01-16T09:52:20.000+01:00"}, {"url": "https://fhir.centraxx.de/extension/sample/sampleLocation", "extension": [{"url": "https://fhir.centraxx.de/extension/sample/sampleLocationPath", "valueString": "NUM --> Klinikum W\u00fcrzburg --> Ultra-Tiefk\u00fchlschrank POP -80\u00b0C"}]}, {"url": "https://fhir.centraxx.de/extension/sample/organizationUnit", "valueReference": {"identifier": {"value": "NUM_W_POP"}}}, {"url": "https://fhir.centraxx.de/extension/sample/derivalDate", "valueDateTime": "2024-01-16T09:45:25.000+01:00"}, {"url": "https://fhir.centraxx.de/extension/sampleCategory", "valueCoding": {"system": "urn:centraxx", "code": "DERIVED"}}, {"url": "https://fhir.centraxx.de/extension/sprec", "extension": [{"url": "https://fhir.centraxx.de/extension/sprec/useSprec", "valueBoolean": false}, {"url": "https://fhir.centraxx.de/extension/sprec/stockProcessing", "valueCoding": {"system": "urn:centraxx", "code": "Sprec-B"}}]}], "identifier": [{"type": {"coding": [{"system": "urn:centraxx", "code": "SAMPLEID"}]}, "value": "4080426722"}], "status": "available", "type": {"coding": [{"system": "urn:centraxx", "code": "CIT"}]}, "subject": {"identifier": {"type": {"coding": [{"system": "urn:centraxx", "code": "LIMSPSN"}]}, "value": "lims_212336720"}}, "parent": [{"reference": "Specimen/357986"}], "collection": {"collectedDateTime": "2024-01-16T08:50:44+01:00", "quantity": {"value": 350, "unit": "MICL", "system": "urn:centraxx"}}, "container": [{"identifier": [{"system": "urn:centraxx", "value": "NUM_AliContainer"}], "capacity": {"value": 350, "unit": "MICL", "system": "urn:centraxx"}, "specimenQuantity": {"value": 350, "unit": "MICL", "system": "urn:centraxx"}}]}, "request": {"method": "POST", "url": "Specimen/357987"}}, {"fullUrl": "Specimen/357989", "resource": {"resourceType": "Specimen", "id": "357989", "extension": [{"url": "https://fhir.centraxx.de/extension/updateWithOverwrite", "valueBoolean": false}, {"url": "https://fhir.centraxx.de/extension/sample/repositionDate", "valueDateTime": "2024-01-16T09:52:20.000+01:00"}, {"url": "https://fhir.centraxx.de/extension/sample/sampleLocation", "extension": [{"url": "https://fhir.centraxx.de/extension/sample/sampleLocationPath", "valueString": "NUM --> Klinikum W\u00fcrzburg --> Ultra-Tiefk\u00fchlschrank POP -80\u00b0C"}]}, {"url": "https://fhir.centraxx.de/extension/sample/organizationUnit", "valueReference": {"identifier": {"value": "NUM_W_POP"}}}, {"url": "https://fhir.centraxx.de/extension/sample/derivalDate", "valueDateTime": "2024-01-16T09:45:29.000+01:00"}, {"url": "https://fhir.centraxx.de/extension/sampleCategory", "valueCoding": {"system": "urn:centraxx", "code": "DERIVED"}}, {"url": "https://fhir.centraxx.de/extension/sprec", "extension": [{"url": "https://fhir.centraxx.de/extension/sprec/useSprec", "valueBoolean": false}, {"url": "https://fhir.centraxx.de/extension/sprec/stockProcessing", "valueCoding": {"system": "urn:centraxx", "code": "Sprec-B"}}]}], "identifier": [{"type": {"coding": [{"system": "urn:centraxx", "code": "SAMPLEID"}]}, "value": "4080426709"}], "status": "available", "type": {"coding": [{"system": "urn:centraxx", "code": "CIT"}]}, "subject": {"identifier": {"type": {"coding": [{"system": "urn:centraxx", "code": "LIMSPSN"}]}, "value": "lims_212336720"}}, "parent": [{"reference": "Specimen/357988"}], "collection": {"collectedDateTime": "2024-01-16T08:50:44+01:00", "quantity": {"value": 350, "unit": "MICL", "system": "urn:centraxx"}}, "container": [{"identifier": [{"system": "urn:centraxx", "value": "NUM_AliContainer"}], "capacity": {"value": 350, "unit": "MICL", "system": "urn:centraxx"}, "specimenQuantity": {"value": 350, "unit": "MICL", "system": "urn:centraxx"}}]}, "request": {"method": "POST", "url": "Specimen/357989"}}, {"fullUrl": "Specimen/357991", "resource": {"resourceType": "Specimen", "id": "357991", "extension": [{"url": "https://fhir.centraxx.de/extension/updateWithOverwrite", "valueBoolean": false}, {"url": "https://fhir.centraxx.de/extension/sample/repositionDate", "valueDateTime": "2024-01-16T09:52:20.000+01:00"}, {"url": "https://fhir.centraxx.de/extension/sample/sampleLocation", "extension": [{"url": "https://fhir.centraxx.de/extension/sample/sampleLocationPath", "valueString": "NUM --> Klinikum W\u00fcrzburg --> Ultra-Tiefk\u00fchlschrank POP -80\u00b0C"}]}, {"url": "https://fhir.centraxx.de/extension/sample/organizationUnit", "valueReference": {"identifier": {"value": "NUM_W_POP"}}}, {"url": "https://fhir.centraxx.de/extension/sample/derivalDate", "valueDateTime": "2024-01-16T09:45:31.000+01:00"}, {"url": "https://fhir.centraxx.de/extension/sampleCategory", "valueCoding": {"system": "urn:centraxx", "code": "DERIVED"}}, {"url": "https://fhir.centraxx.de/extension/sprec", "extension": [{"url": "https://fhir.centraxx.de/extension/sprec/useSprec", "valueBoolean": false}, {"url": "https://fhir.centraxx.de/extension/sprec/stockProcessing", "valueCoding": {"system": "urn:centraxx", "code": "Sprec-B"}}]}], "identifier": [{"type": {"coding": [{"system": "urn:centraxx", "code": "SAMPLEID"}]}, "value": "4080426721"}], "status": "available", "type": {"coding": [{"system": "urn:centraxx", "code": "CIT"}]}, "subject": {"identifier": {"type": {"coding": [{"system": "urn:centraxx", "code": "LIMSPSN"}]}, "value": "lims_212336720"}}, "parent": [{"reference": "Specimen/357990"}], "collection": {"collectedDateTime": "2024-01-16T08:50:44+01:00", "quantity": {"value": 350, "unit": "MICL", "system": "urn:centraxx"}}, "container": [{"identifier": [{"system": "urn:centraxx", "value": "NUM_AliContainer"}], "capacity": {"value": 350, "unit": "MICL", "system": "urn:centraxx"}, "specimenQuantity": {"value": 350, "unit": "MICL", "system": "urn:centraxx"}}]}, "request": {"method": "POST", "url": "Specimen/357991"}}, {"fullUrl": "Specimen/357997", "resource": {"resourceType": "Specimen", "id": "357997", "extension": [{"url": "https://fhir.centraxx.de/extension/updateWithOverwrite", "valueBoolean": false}, {"url": "https://fhir.centraxx.de/extension/sample/repositionDate", "valueDateTime": "2024-01-16T09:52:20.000+01:00"}, {"url": "https://fhir.centraxx.de/extension/sample/sampleLocation", "extension": [{"url": "https://fhir.centraxx.de/extension/sample/sampleLocationPath", "valueString": "NUM --> Klinikum W\u00fcrzburg --> Ultra-Tiefk\u00fchlschrank POP -80\u00b0C"}]}, {"url": "https://fhir.centraxx.de/extension/sample/organizationUnit", "valueReference": {"identifier": {"value": "NUM_W_POP"}}}, {"url": "https://fhir.centraxx.de/extension/sample/derivalDate", "valueDateTime": "2024-01-16T09:47:35.000+01:00"}, {"url": "https://fhir.centraxx.de/extension/sampleCategory", "valueCoding": {"system": "urn:centraxx", "code": "DERIVED"}}, {"url": "https://fhir.centraxx.de/extension/sprec", "extension": [{"url": "https://fhir.centraxx.de/extension/sprec/useSprec", "valueBoolean": false}, {"url": "https://fhir.centraxx.de/extension/sprec/stockProcessing", "valueCoding": {"system": "urn:centraxx", "code": "Sprec-B"}}]}], "identifier": [{"type": {"coding": [{"system": "urn:centraxx", "code": "SAMPLEID"}]}, "value": "4080431619"}], "status": "available", "type": {"coding": [{"system": "urn:centraxx", "code": "EDTA"}]}, "subject": {"identifier": {"type": {"coding": [{"system": "urn:centraxx", "code": "LIMSPSN"}]}, "value": "lims_212336720"}}, "parent": [{"reference": "Specimen/357996"}], "collection": {"collectedDateTime": "2024-01-16T08:50:12+01:00", "quantity": {"value": 350, "unit": "MICL", "system": "urn:centraxx"}}, "container": [{"identifier": [{"system": "urn:centraxx", "value": "NUM_AliContainer"}], "capacity": {"value": 350, "unit": "MICL", "system": "urn:centraxx"}, "specimenQuantity": {"value": 350, "unit": "MICL", "system": "urn:centraxx"}}]}, "request": {"method": "POST", "url": "Specimen/357997"}}]}